logicsponge/processmining/__init__.py
logicsponge/processmining/algorithms_and_structures.py
logicsponge/processmining/automata.py
logicsponge/processmining/config.py
logicsponge/processmining/data_analysis.py
logicsponge/processmining/data_utils.py
logicsponge/processmining/models.py
logicsponge/processmining/neural_networks.py
logicsponge/processmining/streaming.py
logicsponge/processmining/test_data.py
logicsponge/processmining/types.py
logicsponge/processmining/utils.py
logicsponge_processmining-0.0.5.dist-info/METADATA
logicsponge_processmining-0.0.5.dist-info/WHEEL
logicsponge_processmining-0.0.5.dist-info/licenses/LICENSE
logicsponge_processmining-0.0.5.dist-info/RECORD
