Metadata-Version: 2.3
Name: logicsponge-processmining
Version: 0.0.5
Summary: A real-time data processing pipeline
Project-URL: Repository, https://github.com/innatelogic/logicsponge-processmining.git
Author-email: Benedikt Bollig <bollig@lmf.cnrs.fr>, Matthias Függer <mfuegger@lmf.cnrs.fr>, Thomas Nowak <thomas@thomasnowak.net>
Maintainer-email: Benedikt Bollig <bollig@lmf.cnrs.fr>, Matthias Függer <mfuegger@lmf.cnrs.fr>, Thomas Nowak <thomas@thomasnowak.net>
License:                                  Apache License
Keywords: data processing,real-time,time series
Classifier: Development Status :: 4 - Beta
Classifier: Programming Language :: Python
Requires-Python: >=3.11
Requires-Dist: aalpy
Requires-Dist: dash
Requires-Dist: dash-cytoscape
Requires-Dist: logicsponge
Requires-Dist: matplotlib
Requires-Dist: numpy
Requires-Dist: pandas
Requires-Dist: pandas-stubs
Requires-Dist: pm4py
Requires-Dist: pot
Requires-Dist: requests
Requires-Dist: sortedcontainers
Requires-Dist: torch
Requires-Dist: tqdm
